twidgets/__init__.py
twidgets/__main__.py
twidgets/config.py
twidgets/logo.py
twidgets/path.py
twidgets/system.py
terminal_widgets-1.25.dist-info/LICENSE
terminal_widgets-1.25.dist-info/METADATA
terminal_widgets-1.25.dist-info/WHEEL
terminal_widgets-1.25.dist-info/entry_points.txt
terminal_widgets-1.25.dist-info/top_level.txt
terminal_widgets-1.25.dist-info/RECORD
