Metadata-Version: 2.1
Name: terminal-widgets
Version: 1.25
Summary: A fully functional program for Terminal to show information about system, display, shell, package and many more.
Author: Im Geek (Ankush Bhagat)
Author-email: <imegeek@gmail.com>
Keywords: python,style,terminal,widgets,sysfetch
Classifier: Intended Audience :: Developers
Classifier: Programming Language :: Python :: 3
Classifier: Operating System :: Unix
Classifier: Operating System :: MacOS :: MacOS X
Classifier: Operating System :: Microsoft :: Windows
License-File: LICENSE
Requires-Dist: py-cpuinfo
Requires-Dist: psutil
Requires-Dist: rich
Requires-Dist: rich-argparse
Requires-Dist: requests
